{
  "metadata": {
    "simulation_date": "2025-07-28T07:34:29.322702",
    "total_battles": 1500,
    "battles_per_matchup": 100,
    "languages_simulated": 6,
    "random_seed": null
  },
  "language_performance": {
    "python": {
      "total_battles": 500,
      "wins": 253,
      "losses": 247,
      "win_rate": 0.506,
      "avg_hp_remaining_when_winning": 23.636363636363637,
      "avg_turns_when_winning": 8.090909090909092,
      "avg_damage_dealt": 73.11,
      "language_name": "Python"
    },
    "go": {
      "total_battles": 500,
      "wins": 267,
      "losses": 233,
      "win_rate": 0.534,
      "avg_hp_remaining_when_winning": 41.018582686839686,
      "avg_turns_when_winning": 6.037453183520599,
      "avg_damage_dealt": 84.6560513239717,
      "language_name": "Go"
    },
    "rust": {
      "total_battles": 500,
      "wins": 167,
      "losses": 333,
      "win_rate": 0.334,
      "avg_hp_remaining_when_winning": 22.994011976047904,
      "avg_turns_when_winning": 7.970059880239521,
      "avg_damage_dealt": 68.19,
      "language_name": "Rust"
    },
    "ocaml": {
      "total_battles": 500,
      "wins": 263,
      "losses": 237,
      "win_rate": 0.526,
      "avg_hp_remaining_when_winning": 67.64594678968783,
      "avg_turns_when_winning": 2.7680608365019013,
      "avg_damage_dealt": 112.90333698444029,
      "language_name": "OCaml"
    },
    "csharp": {
      "total_battles": 500,
      "wins": 358,
      "losses": 142,
      "win_rate": 0.716,
      "avg_hp_remaining_when_winning": 55.40268339779793,
      "avg_turns_when_winning": 4.0474860335195535,
      "avg_damage_dealt": 110.34430025719638,
      "language_name": "C#"
    },
    "javascript": {
      "total_battles": 500,
      "wins": 192,
      "losses": 308,
      "win_rate": 0.384,
      "avg_hp_remaining_when_winning": 62.847182151052785,
      "avg_turns_when_winning": 2.5677083333333335,
      "avg_damage_dealt": 79.37553951195093,
      "language_name": "JavaScript & TypeScript"
    }
  },
  "ability_performance": {
    "python_0": {
      "language_id": "python",
      "language_name": "Python",
      "ability_name": "Rapid Prototype",
      "ability_index": 0,
      "ability_type": "Passive",
      "ability_power": 10,
      "total_uses": 233,
      "wins_with_ability": 92,
      "losses_with_ability": 141,
      "win_rate_with_ability": 0.3948497854077253,
      "avg_damage_with_ability": 66.18025751072962
    },
    "python_1": {
      "language_id": "python",
      "language_name": "Python",
      "ability_name": "Ecosystem Call",
      "ability_index": 1,
      "ability_type": "Utility",
      "ability_power": 15,
      "total_uses": 267,
      "wins_with_ability": 161,
      "losses_with_ability": 106,
      "win_rate_with_ability": 0.602996254681648,
      "avg_damage_with_ability": 79.15730337078652
    },
    "go_0": {
      "language_id": "go",
      "language_name": "Go",
      "ability_name": "Fast Compilation",
      "ability_index": 0,
      "ability_type": "Passive",
      "ability_power": 10,
      "total_uses": 270,
      "wins_with_ability": 93,
      "losses_with_ability": 177,
      "win_rate_with_ability": 0.34444444444444444,
      "avg_damage_with_ability": 68.14814814814815
    },
    "go_1": {
      "language_id": "go",
      "language_name": "Go",
      "ability_name": "Goroutine Swarm",
      "ability_index": 1,
      "ability_type": "Special",
      "ability_power": 45,
      "total_uses": 230,
      "wins_with_ability": 174,
      "losses_with_ability": 56,
      "win_rate_with_ability": 0.7565217391304347,
      "avg_damage_with_ability": 104.03489418254716
    },
    "rust_0": {
      "language_id": "rust",
      "language_name": "Rust",
      "ability_name": "Borrow Checker",
      "ability_index": 0,
      "ability_type": "Passive",
      "ability_power": 10,
      "total_uses": 263,
      "wins_with_ability": 54,
      "losses_with_ability": 209,
      "win_rate_with_ability": 0.20532319391634982,
      "avg_damage_with_ability": 61.254752851711025
    },
    "rust_1": {
      "language_id": "rust",
      "language_name": "Rust",
      "ability_name": "Zero-Cost Abstraction",
      "ability_index": 1,
      "ability_type": "Buff",
      "ability_power": 15,
      "total_uses": 237,
      "wins_with_ability": 113,
      "losses_with_ability": 124,
      "win_rate_with_ability": 0.4767932489451477,
      "avg_damage_with_ability": 75.88607594936708
    },
    "ocaml_0": {
      "language_id": "ocaml",
      "language_name": "OCaml",
      "ability_name": "Type Inference",
      "ability_index": 0,
      "ability_type": "Passive",
      "ability_power": 10,
      "total_uses": 250,
      "wins_with_ability": 23,
      "losses_with_ability": 227,
      "win_rate_with_ability": 0.092,
      "avg_damage_with_ability": 63.76
    },
    "ocaml_1": {
      "language_id": "ocaml",
      "language_name": "OCaml",
      "ability_name": "Pattern Matching",
      "ability_index": 1,
      "ability_type": "Special",
      "ability_power": 80,
      "total_uses": 250,
      "wins_with_ability": 240,
      "losses_with_ability": 10,
      "win_rate_with_ability": 0.96,
      "avg_damage_with_ability": 162.04667396888058
    },
    "csharp_0": {
      "language_id": "csharp",
      "language_name": "C#",
      "ability_name": "Garbage Collection",
      "ability_index": 0,
      "ability_type": "Recovery",
      "ability_power": 15,
      "total_uses": 252,
      "wins_with_ability": 133,
      "losses_with_ability": 119,
      "win_rate_with_ability": 0.5277777777777778,
      "avg_damage_with_ability": 81.60714285714286
    },
    "csharp_1": {
      "language_id": "csharp",
      "language_name": "C#",
      "ability_name": "LINQ Query",
      "ability_index": 1,
      "ability_type": "Special",
      "ability_power": 70,
      "total_uses": 248,
      "wins_with_ability": 225,
      "losses_with_ability": 23,
      "win_rate_with_ability": 0.907258064516129,
      "avg_damage_with_ability": 139.54496019596044
    },
    "javascript_0": {
      "language_id": "javascript",
      "language_name": "JavaScript & TypeScript",
      "ability_name": "Asynchronous Promise",
      "ability_index": 0,
      "ability_type": "Special",
      "ability_power": 60,
      "total_uses": 239,
      "wins_with_ability": 192,
      "losses_with_ability": 47,
      "win_rate_with_ability": 0.803347280334728,
      "avg_damage_with_ability": 100.492760485253
    },
    "javascript_1": {
      "language_id": "javascript",
      "language_name": "JavaScript & TypeScript",
      "ability_name": "Framework Flux",
      "ability_index": 1,
      "ability_type": "Passive",
      "ability_power": 10,
      "total_uses": 261,
      "wins_with_ability": 0,
      "losses_with_ability": 261,
      "win_rate_with_ability": 0.0,
      "avg_damage_with_ability": 60.03831417624521
    }
  },
  "matchup_statistics": {
    "python_vs_go": {
      "language1": "python",
      "language2": "go",
      "language1_name": "Python",
      "language2_name": "Go",
      "total_battles": 100,
      "language1_wins": 52,
      "language2_wins": 48,
      "language1_win_rate": 0.52,
      "language2_win_rate": 0.48
    },
    "python_vs_rust": {
      "language1": "python",
      "language2": "rust",
      "language1_name": "Python",
      "language2_name": "Rust",
      "total_battles": 100,
      "language1_wins": 79,
      "language2_wins": 21,
      "language1_win_rate": 0.79,
      "language2_win_rate": 0.21
    },
    "python_vs_ocaml": {
      "language1": "python",
      "language2": "ocaml",
      "language1_name": "Python",
      "language2_name": "OCaml",
      "total_battles": 100,
      "language1_wins": 54,
      "language2_wins": 46,
      "language1_win_rate": 0.54,
      "language2_win_rate": 0.46
    },
    "python_vs_csharp": {
      "language1": "python",
      "language2": "csharp",
      "language1_name": "Python",
      "language2_name": "C#",
      "total_battles": 100,
      "language1_wins": 21,
      "language2_wins": 79,
      "language1_win_rate": 0.21,
      "language2_win_rate": 0.79
    },
    "python_vs_javascript": {
      "language1": "python",
      "language2": "javascript",
      "language1_name": "Python",
      "language2_name": "JavaScript & TypeScript",
      "total_battles": 100,
      "language1_wins": 47,
      "language2_wins": 53,
      "language1_win_rate": 0.47,
      "language2_win_rate": 0.53
    },
    "go_vs_rust": {
      "language1": "go",
      "language2": "rust",
      "language1_name": "Go",
      "language2_name": "Rust",
      "total_battles": 100,
      "language1_wins": 71,
      "language2_wins": 29,
      "language1_win_rate": 0.71,
      "language2_win_rate": 0.29
    },
    "go_vs_ocaml": {
      "language1": "go",
      "language2": "ocaml",
      "language1_name": "Go",
      "language2_name": "OCaml",
      "total_battles": 100,
      "language1_wins": 52,
      "language2_wins": 48,
      "language1_win_rate": 0.52,
      "language2_win_rate": 0.48
    },
    "go_vs_csharp": {
      "language1": "go",
      "language2": "csharp",
      "language1_name": "Go",
      "language2_name": "C#",
      "total_battles": 100,
      "language1_wins": 29,
      "language2_wins": 71,
      "language1_win_rate": 0.29,
      "language2_win_rate": 0.71
    },
    "go_vs_javascript": {
      "language1": "go",
      "language2": "javascript",
      "language1_name": "Go",
      "language2_name": "JavaScript & TypeScript",
      "total_battles": 100,
      "language1_wins": 67,
      "language2_wins": 33,
      "language1_win_rate": 0.67,
      "language2_win_rate": 0.33
    },
    "rust_vs_ocaml": {
      "language1": "rust",
      "language2": "ocaml",
      "language1_name": "Rust",
      "language2_name": "OCaml",
      "total_battles": 100,
      "language1_wins": 42,
      "language2_wins": 58,
      "language1_win_rate": 0.42,
      "language2_win_rate": 0.58
    },
    "rust_vs_csharp": {
      "language1": "rust",
      "language2": "csharp",
      "language1_name": "Rust",
      "language2_name": "C#",
      "total_battles": 100,
      "language1_wins": 24,
      "language2_wins": 76,
      "language1_win_rate": 0.24,
      "language2_win_rate": 0.76
    },
    "rust_vs_javascript": {
      "language1": "rust",
      "language2": "javascript",
      "language1_name": "Rust",
      "language2_name": "JavaScript & TypeScript",
      "total_battles": 100,
      "language1_wins": 51,
      "language2_wins": 49,
      "language1_win_rate": 0.51,
      "language2_win_rate": 0.49
    },
    "ocaml_vs_csharp": {
      "language1": "ocaml",
      "language2": "csharp",
      "language1_name": "OCaml",
      "language2_name": "C#",
      "total_battles": 100,
      "language1_wins": 39,
      "language2_wins": 61,
      "language1_win_rate": 0.39,
      "language2_win_rate": 0.61
    },
    "ocaml_vs_javascript": {
      "language1": "ocaml",
      "language2": "javascript",
      "language1_name": "OCaml",
      "language2_name": "JavaScript & TypeScript",
      "total_battles": 100,
      "language1_wins": 72,
      "language2_wins": 28,
      "language1_win_rate": 0.72,
      "language2_win_rate": 0.28
    },
    "csharp_vs_javascript": {
      "language1": "csharp",
      "language2": "javascript",
      "language1_name": "C#",
      "language2_name": "JavaScript & TypeScript",
      "total_battles": 100,
      "language1_wins": 71,
      "language2_wins": 29,
      "language1_win_rate": 0.71,
      "language2_win_rate": 0.29
    }
  },
  "raw_results": [
    {
      "battle_num": 0,
      "language1": "python",
      "language2": "go",
      "ability1_index": 1,
      "ability2_index": 0,
      "winner": "python",
      "loser": "go",
      "winner_hp_remaining": 40,
      "turns_taken": 7,
      "winner_ability_used": "Ecosystem Call",
      "loser_ability_used": "Fast Compilation",
      "damage_dealt": {
        "python": 105,
        "go": 60
      }
    },
    {
      "battle_num": 1,
      "language1": "python",
      "language2": "go",
      "ability1_index": 0,
      "ability2_index": 1,
      "winner": "go",
      "loser": "python",
      "winner_hp_remaining": 50,
      "turns_taken": 5,
      "winner_ability_used": "Goroutine Swarm",
      "loser_ability_used": "Rapid Prototype",
      "damage_dealt": {
        "python": 50,
        "go": 126.35121678527699
      }
    },
    {
      "battle_num": 2,
      "language1": "python",
      "language2": "go",
      "ability1_index": 0,
      "ability2_index": 0,
      "winner": "python",
      "loser": "go",
      "winner_hp_remaining": 10,
      "turns_taken": 10,
      "winner_ability_used": "Rapid Prototype",
      "loser_ability_used": "Fast Compilation",
      "damage_dealt": {
        "python": 100,
        "go": 90
      }
    },
    {
      "battle_num": 3,
      "language1": "python",
      "language2": "go",
      "ability1_index": 1,
      "ability2_index": 1,
      "winner": "go",
      "loser": "python",
      "winner_hp_remaining": 40,
      "turns_taken": 4,
      "winner_ability_used": "Goroutine Swarm",
      "loser_ability_used": "Ecosystem Call",
      "damage_dealt": {
        "python": 60,
        "go": 124.63240126985508
      }
    },
    {
      "battle_num": 4,
      "language1": "python",
      "language2": "go",
      "ability1_index": 0,
      "ability2_index": 0,
      "winner": "python",
      "loser": "go",
      "winner_hp_remaining": 10,
      "turns_taken": 10,
      "winner_ability_used": "Rapid Prototype",
      "loser_ability_used": "Fast Compilation",
      "damage_dealt": {
        "python": 100,
        "go": 90
      }
    },
    {
      "battle_num": 5,
      "language1": "python",
      "language2": "go",
      "ability1_index": 1,
      "ability2_index": 1,
      "winner": "go",
      "loser": "python",
      "winner_hp_remaining": 55,
      "turns_taken": 3,
      "winner_ability_used": "Goroutine Swarm",
      "loser_ability_used": "Ecosystem Call",
      "damage_dealt": {
        "python": 45,
        "go": 127.74575944202836
      }
    },
    {
      "battle_num": 6,
      "language1": "python",
      "language2": "go",
      "ability1_index": 0,
      "ability2_index": 0,
      "winner": "python",
      "loser": "go",
      "winner_hp_remaining": 10,
      "turns_taken": 10,
      "winner_ability_used": "Rapid Prototype",
      "loser_ability_used": "Fast Compilation",
      "damage_dealt": {
        "python": 100,
        "go": 90
      }
    },
    {
      "battle_num": 7,
      "language1": "python",
      "language2": "go",
      "ability1_index": 0,
      "ability2_index": 1,
      "winner": "go",
      "loser": "python",
      "winner_hp_remaining": 60,
      "turns_taken": 4,
      "winner_ability_used": "Goroutine Swarm",
      "loser_ability_used": "Rapid Prototype",
      "damage_dealt": {
        "python": 40,
        "go": 121.42137620830252
      }
    },
    {
      "battle_num": 8,
      "language1": "python",
      "language2": "go",
      "ability1_index": 1,
      "ability2_index": 0,
      "winner": "python",
      "loser": "go",
      "winner_hp_remaining": 40,
      "turns_taken": 7,
      "winner_ability_used": "Ecosystem Call",
      "loser_ability_used": "Fast Compilation",
      "damage_dealt": {
        "python": 105,
        "go": 60
      }
    },
    {
      "battle_num": 9,
      "language1": "python",
      "language2": "go",
      "ability1_index": 1,
      "ability2_index": 1,
      "winner": "go",
      "loser": "python",
      "winner_hp_remaining": 25,
      "turns_taken": 5,
      "winner_ability_used": "Goroutine Swarm",
      "loser_ability_used": "Ecosystem Call",
      "damage_dealt": {
        "python": 75,
        "go": 126.06829842288893
      }
    },
    {
      "battle_num": 10,
      "language1": "python",
      "language2": "go",
      "ability1_index": 1,
      "ability2_index": 0,
      "winner": "python",
      "loser": "go",
      "winner_hp_remaining": 40,
      "turns_taken": 7,
      "winner_ability_used": "Ecosystem Call",
      "loser_ability_used": "Fast Compilation",
      "damage_dealt": {
        "python": 105,
        "go": 60
      }
    },
    {
      "battle_num": 11,
      "language1": "python",
      "language2": "go",
      "ability1_index": 0,
      "ability2_index": 1,
      "winner": "go",
      "loser": "python",
      "winner_hp_remaining": 70,
      "turns_taken": 3,
      "winner_ability_used": "Goroutine Swarm",
      "loser_ability_used": "Rapid Prototype",
      "damage_dealt": {
        "python": 30,
        "go": 127.02910156688345
      }
    },
    {
      "battle_num": 12,
      "language1": "python",
      "language2": "go",
      "ability1_index": 0,
      "ability2_index": 1,
      "winner": "go",
      "loser": "python",
      "winner_hp_remaining": 70,
      "turns_taken": 3,
      "winner_ability_used": "Goroutine Swarm",
      "loser_ability_used": "Rapid Prototype",
      "damage_dealt": {
        "python": 30,
        "go": 125.56565062564113
      }
    },
    {
      "battle_num": 13,
      "language1": "python",
      "language2": "go",
      "ability1_index": 1,
      "ability2_index": 0,
      "winner": "python",
      "loser": "go",
      "winner_hp_remaining": 40,
      "turns_taken": 7,
      "winner_ability_used": "Ecosystem Call",
      "loser_ability_used": "Fast Compilation",
      "damage_dealt": {
        "python": 105,
        "go": 60
      }
    },
    {
      "battle_num": 14,
      "language1": "python",
      "language2": "go",
      "ability1_index": 1,
      "ability2_index": 0,
      "winner": "python",
      "loser": "go",
      "winner_hp_remaining": 40,
      "turns_taken": 7,
      "winner_ability_used": "Ecosystem Call",
      "loser_ability_used": "Fast Compilation",
      "damage_dealt": {
        "python": 105,
        "go": 60
      }
    },
    {
      "battle_num": 15,
      "language1": "python",
      "language2": "go",
      "ability1_index": 1,
      "ability2_index": 0,
      "winner": "python",
      "loser": "go",
      "winner_hp_remaining": 40,
      "turns_taken": 7,
      "winner_ability_used": "Ecosystem Call",
      "loser_ability_used": "Fast Compilation",
      "damage_dealt": {
        "python": 105,
        "go": 60
      }
    },
    {
      "battle_num": 16,
      "language1": "python",
      "language2": "go",
      "ability1_index": 1,
      "ability2_index": 1,
      "winner": "go",
      "loser": "python",
      "winner_hp_remaining": 55,
      "turns_taken": 3,
      "winner_ability_used": "Goroutine Swarm",
      "loser_ability_used": "Ecosystem Call",
      "damage_dealt": {
        "python": 45,
        "go": 130.80775303614504
      }
    },
    {
      "battle_num": 17,
      "language1": "python",
      "language2": "go",
      "ability1_index": 1,
      "ability2_index": 0,
      "winner": "python",
      "loser": "go",
      "winner_hp_remaining": 40,
      "turns_taken": 7,
      "winner_ability_used": "Ecosystem Call",
      "loser_ability_used": "Fast Compilation",
      "damage_dealt": {
        "python": 105,
        "go": 60
      }
    },
    {
      "battle_num": 18,
      "language1": "python",
      "language2": "go",
      "ability1_index": 0,
      "ability2_index": 0,
      "winner": "python",
      "loser": "go",
      "winner_hp_remaining": 10,
      "turns_taken": 10,
      "winner_ability_used": "Rapid Prototype",
      "loser_ability_used": "Fast Compilation",
      "damage_dealt": {
        "python": 100,
        "go": 90
      }
    },
    {
      "battle_num": 19,
      "language1": "python",
      "language2": "go",
      "ability1_index": 1,
      "ability2_index": 1,
      "winner": "go",
      "loser": "python",
      "winner_hp_remaining": 55,
      "turns_taken": 3,
      "winner_ability_used": "Goroutine Swarm",
      "loser_ability_used": "Ecosystem Call",
      "damage_dealt": {
        "python": 45,
        "go": 128.57046676200565
      }
    },
    {
      "battle_num": 20,
      "language1": "python",
      "language2": "go",
      "ability1_index": 0,
      "ability2_index": 0,
      "winner": "python",
      "loser": "go",
      "winner_hp_remaining": 10,
      "turns_taken": 10,
      "winner_ability_used": "Rapid Prototype",
      "loser_ability_used": "Fast Compilation",
      "damage_dealt": {
        "python": 100,
        "go": 90
      }
    },
    {
      "battle_num": 21,
      "language1": "python",
      "language2": "go",
      "ability1_index": 0,
      "ability2_index": 1,
      "winner": "go",
      "loser": "python",
      "winner_hp_remaining": 40,
      "turns_taken": 6,
      "winner_ability_used": "Goroutine Swarm",
      "loser_ability_used": "Rapid Prototype",
      "damage_dealt": {
        "python": 60,
        "go": 124.19501131976162
      }
    },
    {
      "battle_num": 22,
      "language1": "python",
      "language2": "go",
      "ability1_index": 0,
      "ability2_index": 0,
      "winner": "python",
      "loser": "go",
      "winner_hp_remaining": 10,
      "turns_taken": 10,
      "winner_ability_used": "Rapid Prototype",
      "loser_ability_used": "Fast Compilation",
      "damage_dealt": {
        "python": 100,
        "go": 90
      }
    },
    {
      "battle_num": 23,
      "language1": "python",
      "language2": "go",
      "ability1_index": 0,
      "ability2_index": 1,
      "winner": "go",
      "loser": "python",
      "winner_hp_remaining": 70,
      "turns_taken": 3,
      "winner_ability_used": "Goroutine Swarm",
      "loser_ability_used": "Rapid Prototype",
      "damage_dealt": {
        "python": 30,
        "go": 121.20542887923087
      }
    },
    {
      "battle_num": 24,
      "language1": "python",
      "language2": "go",
      "ability1_index": 0,
      "ability2_index": 1,
      "winner": "go",
      "loser": "python",
      "winner_hp_remaining": 70,
      "turns_taken": 3,
      "winner_ability_used": "Goroutine Swarm",
      "loser_ability_used": "Rapid Prototype",
      "damage_dealt": {
        "python": 30,
        "go": 123.8164546071939
      }
    },
    {
      "battle_num": 25,
      "language1": "python",
      "language2": "go",
      "ability1_index": 0,
      "ability2_index": 0,
      "winner": "python",
      "loser": "go",
      "winner_hp_remaining": 10,
      "turns_taken": 10,
      "winner_ability_used": "Rapid Prototype",
      "loser_ability_used": "Fast Compilation",
      "damage_dealt": {
        "python": 100,
        "go": 90
      }
    },
    {
      "battle_num": 26,
      "language1": "python",
      "language2": "go",
      "ability1_index": 0,
      "ability2_index": 1,
      "winner": "go",
      "loser": "python",
      "winner_hp_remaining": 70,
      "turns_taken": 3,
      "winner_ability_used": "Goroutine Swarm",
      "loser_ability_used": "Rapid Prototype",
      "damage_dealt": {
        "python": 30,
        "go": 118.35526026728817
      }
    },
    {
      "battle_num": 27,
      "language1": "python",
      "language2": "go",
      "ability1_index": 1,
      "ability2_index": 0,
      "winner": "python",
      "loser": "go",
      "winner_hp_remaining": 40,
      "turns_taken": 7,
      "winner_ability_used": "Ecosystem Call",
      "loser_ability_used": "Fast Compilation",
      "damage_dealt": {
        "python": 105,
        "go": 60
      }
    },
    {
      "battle_num": 28,
      "language1": "python",
      "language2": "go",
      "ability1_index": 1,
      "ability2_index": 0,
      "winner": "python",
      "loser": "go",
      "winner_hp_remaining": 40,
      "turns_taken": 7,
      "winner_ability_used": "Ecosystem Call",
      "loser_ability_used": "Fast Compilation",
      "damage_dealt": {
        "python": 105,
        "go": 60
      }
    },
    {
      "battle_num": 29,
      "language1": "python",
      "language2": "go",
      "ability1_index": 1,
      "ability2_index": 1,
      "winner": "go",
      "loser": "python",
      "winner_hp_remaining": 55,
      "turns_taken": 3,
      "winner_ability_used": "Goroutine Swarm",
      "loser_ability_used": "Ecosystem Call",
      "damage_dealt": {
        "python": 45,
        "go": 122.03787545204986
      }
    },
    {
      "battle_num": 30,
      "language1": "python",
      "language2": "go",
      "ability1_index": 1,
      "ability2_index": 1,
      "winner": "go",
      "loser": "python",
      "winner_hp_remaining": 10,
      "turns_taken": 6,
      "winner_ability_used": "Goroutine Swarm",
      "loser_ability_used": "Ecosystem Call",
      "damage_dealt": {
        "python": 90,
        "go": 126.93871267970536
      }
    },
    {
      "battle_num": 31,
      "language1": "python",
      "language2": "go",
      "ability1_index": 1,
      "ability2_index": 0,
      "winner": "python",
      "loser": "go",
      "winner_hp_remaining": 40,
      "turns_taken": 7,
      "winner_ability_used": "Ecosystem Call",
      "loser_ability_used": "Fast Compilation",
      "damage_dealt": {
        "python": 105,
        "go": 60
      }
    },
    {
      "battle_num": 32,
      "language1": "python",
      "language2": "go",
      "ability1_index": 0,
      "ability2_index": 0,
      "winner": "python",
      "loser": "go",
      "winner_hp_remaining": 10,
      "turns_taken": 10,
      "winner_ability_used": "Rapid Prototype",
      "loser_ability_used": "Fast Compilation",
      "damage_dealt": {
        "python": 100,
        "go": 90
      }
    },
    {
      "battle_num": 33,
      "language1": "python",
      "language2": "go",
      "ability1_index": 1,
      "ability2_index": 0,
      "winner": "python",
      "loser": "go",
      "winner_hp_remaining": 40,
      "turns_taken": 7,
      "winner_ability_used": "Ecosystem Call",
      "loser_ability_used": "Fast Compilation",
      "damage_dealt": {
        "python": 105,
        "go": 60
      }
    },
    {
      "battle_num": 34,
      "language1": "python",
      "language2": "go",
      "ability1_index": 0,
      "ability2_index": 0,
      "winner": "python",
      "loser": "go",
      "winner_hp_remaining": 10,
      "turns_taken": 10,
      "winner_ability_used": "Rapid Prototype",
      "loser_ability_used": "Fast Compilation",
      "damage_dealt": {
        "python": 100,
        "go": 90
      }
    },
    {
      "battle_num": 35,
      "language1": "python",
      "language2": "go",
      "ability1_index": 0,
      "ability2_index": 1,
      "winner": "go",
      "loser": "python",
      "winner_hp_remaining": 40,
      "turns_taken": 6,
      "winner_ability_used": "Goroutine Swarm",
      "loser_ability_used": "Rapid Prototype",
      "damage_dealt": {
        "python": 60,
        "go": 119.63772199849777
      }
    },
    {
      "battle_num": 36,
      "language1": "python",
      "language2": "go",
      "ability1_index": 1,
      "ability2_index": 0,
      "winner": "python",
      "loser": "go",
      "winner_hp_remaining": 40,
      "turns_taken": 7,
      "winner_ability_used": "Ecosystem Call",
      "loser_ability_used": "Fast Compilation",
      "damage_dealt": {
        "python": 105,
        "go": 60
      }
    },
    {
      "battle_num": 37,
      "language1": "python",
      "language2": "go",
      "ability1_index": 0,
      "ability2_index": 1,
      "winner": "go",
      "loser": "python",
      "winner_hp_remaining": 50,
      "turns_taken": 5,
      "winner_ability_used": "Goroutine Swarm",
      "loser_ability_used": "Rapid Prototype",
      "damage_dealt": {
        "python": 50,
        "go": 122.9644189631663
      }
    },
    {
      "battle_num": 38,
      "language1": "python",
      "language2": "go",
      "ability1_index": 0,
      "ability2_index": 1,
      "winner": "go",
      "loser": "python",
      "winner_hp_remaining": 60,
      "turns_taken": 4,
      "winner_ability_used": "Goroutine Swarm",
      "loser_ability_used": "Rapid Prototype",
      "damage_dealt": {
        "python": 40,
        "go": 123.72992794430473
      }
    },
    {
      "battle_num": 39,
      "language1": "python",
      "language2": "go",
      "ability1_index": 1,
      "ability2_index": 0,
      "winner": "python",
      "loser": "go",
      "winner_hp_remaining": 40,
      "turns_taken": 7,
      "winner_ability_used": "Ecosystem Call",
      "loser_ability_used": "Fast Compilation",
      "damage_dealt": {
        "python": 105,
        "go": 60
      }
    },
    {
      "battle_num": 40,
      "language1": "python",
      "language2": "go",
      "ability1_index": 0,
      "ability2_index": 1,
      "winner": "go",
      "loser": "python",
      "winner_hp_remaining": 50,
      "turns_taken": 5,
      "winner_ability_used": "Goroutine Swarm",
      "loser_ability_used": "Rapid Prototype",
      "damage_dealt": {
        "python": 50,
        "go": 126.5416853530451
      }
    },
    {
      "battle_num": 41,
      "language1": "python",
      "language2": "go",
      "ability1_index": 0,
      "ability2_index": 0,
      "winner": "python",
      "loser": "go",
      "winner_hp_remaining": 10,
      "turns_taken": 10,
      "winner_ability_used": "Rapid Prototype",
      "loser_ability_used": "Fast Compilation",
      "damage_dealt": {
        "python": 100,
        "go": 90
      }
    },
    {
      "battle_num": 42,
      "language1": "python",
      "language2": "go",
      "ability1_index": 1,
      "ability2_index": 1,
      "winner": "go",
      "loser": "python",
      "winner_hp_remaining": 25,
      "turns_taken": 5,
      "winner_ability_used": "Goroutine Swarm",
      "loser_ability_used": "Ecosystem Call",
      "damage_dealt": {
        "python": 75,
        "go": 129.1306646334795
      }
    },
    {
      "battle_num": 43,
      "language1": "python",
      "language2": "go",
      "ability1_index": 1,
      "ability2_index": 0,
      "winner": "python",
      "loser": "go",
      "winner_hp_remaining": 40,
      "turns_taken": 7,
      "winner_ability_used": "Ecosystem Call",
      "loser_ability_used": "Fast Compilation",
      "damage_dealt": {
        "python": 105,
        "go": 60
      }
    },
    {
      "battle_num": 44,
      "language1": "python",
      "language2": "go",
      "ability1_index": 0,
      "ability2_index": 0,
      "winner": "python",
      "loser": "go",
      "winner_hp_remaining": 10,
      "turns_taken": 10,
      "winner_ability_used": "Rapid Prototype",
      "loser_ability_used": "Fast Compilation",
      "damage_dealt": {
        "python": 100,
        "go": 90
      }
    },
    {
      "battle_num": 45,
      "language1": "python",
      "language2": "go",
      "ability1_index": 0,
      "ability2_index": 0,
      "winner": "python",
      "loser": "go",
      "winner_hp_remaining": 10,
      "turns_taken": 10,
      "winner_ability_used": "Rapid Prototype",
      "loser_ability_used": "Fast Compilation",
      "damage_dealt": {
        "python": 100,
        "go": 90
      }
    },
    {
      "battle_num": 46,
      "language1": "python",
      "language2": "go",
      "ability1_index": 1,
      "ability2_index": 1,
      "winner": "go",
      "loser": "python",
      "winner_hp_remaining": 55,
      "turns_taken": 3,
      "winner_ability_used": "Goroutine Swarm",
      "loser_ability_used": "Ecosystem Call",
      "damage_dealt": {
        "python": 45,
        "go": 125.02867415381837
      }
    },
    {
      "battle_num": 47,
      "language1": "python",
      "language2": "go",
      "ability1_index": 0,
      "ability2_index": 1,
      "winner": "go",
      "loser": "python",
      "winner_hp_remaining": 70,
      "turns_taken": 3,
      "winner_ability_used": "Goroutine Swarm",
      "loser_ability_used": "Rapid Prototype",
      "damage_dealt": {
        "python": 30,
        "go": 125.0124746054588
      }
    },
    {
      "battle_num": 48,
      "language1": "python",
      "language2": "go",
      "ability1_index": 0,
      "ability2_index": 0,
      "winner": "python",
      "loser": "go",
      "winner_hp_remaining": 10,
      "turns_taken": 10,
      "winner_ability_used": "Rapid Prototype",
      "loser_ability_used": "Fast Compilation",
      "damage_dealt": {
        "python": 100,
        "go": 90
      }
    },
    {
      "battle_num": 49,
      "language1": "python",
      "language2": "go",
      "ability1_index": 0,
      "ability2_index": 0,
      "winner": "python",
      "loser": "go",
      "winner_hp_remaining": 10,
      "turns_taken": 10,
      "winner_ability_used": "Rapid Prototype",
      "loser_ability_used": "Fast Compilation",
      "damage_dealt": {
        "python": 100,
        "go": 90
      }
    },
    {
      "battle_num": 50,
      "language1": "python",
      "language2": "go",
      "ability1_index": 1,
      "ability2_index": 1,
      "winner": "go",
      "loser": "python",
      "winner_hp_remaining": 55,
      "turns_taken": 3,
      "winner_ability_used": "Goroutine Swarm",
      "loser_ability_used": "Ecosystem Call",
      "damage_dealt": {
        "python": 45,
        "go": 125.98533728806336
      }
    },
    {
      "battle_num": 51,
      "language1": "python",
      "language2": "go",
      "ability1_index": 1,
      "ability2_index": 0,
      "winner": "python",
      "loser": "go",
      "winner_hp_remaining": 40,
      "turns_taken": 7,
      "winner_ability_used": "Ecosystem Call",
      "loser_ability_used": "Fast Compilation",
      "damage_dealt": {
        "python": 105,
        "go": 60
      }
    },
    {
      "battle_num": 52,
      "language1": "python",
      "language2": "go",
      "ability1_index": 1,
      "ability2_index": 0,
      "winner": "python",
      "loser": "go",
      "winner_hp_remaining": 40,
      "turns_taken": 7,
      "winner_ability_used": "Ecosystem Call",
      "loser_ability_used": "Fast Compilation",
      "damage_dealt": {
        "python": 105,
        "go": 60
      }
    },
    {
      "battle_num": 53,
      "language1": "python",
      "language2": "go",
      "ability1_index": 1,
      "ability2_index": 0,
      "winner": "python",
      "loser": "go",
      "winner_hp_remaining": 40,
      "turns_taken": 7,
      "winner_ability_used": "Ecosystem Call",
      "loser_ability_used": "Fast Compilation",
      "damage_dealt": {
        "python": 105,
        "go": 60
      }
    },
    {
      "battle_num": 54,
      "language1": "python",
      "language2": "go",
      "ability1_index": 1,
      "ability2_index": 1,
      "winner": "go",
      "loser": "python",
      "winner_hp_remaining": 55,
      "turns_taken": 3,
      "winner_ability_used": "Goroutine Swarm",
      "loser_ability_used": "Ecosystem Call",
      "damage_dealt": {
        "python": 45,
        "go": 121.99593019485954
      }
    },
    {
      "battle_num": 55,
      "language1": "python",
      "language2": "go",
      "ability1_index": 1,
      "ability2_index": 1,
      "winner": "go",
      "loser": "python",
      "winner_hp_remaining": 55,
      "turns_taken": 3,
      "winner_ability_used": "Goroutine Swarm",
      "loser_ability_used": "Ecosystem Call",
      "damage_dealt": {
        "python": 45,
        "go": 124.65611745429447
      }
    },
    {
      "battle_num": 56,
      "language1": "python",
      "language2": "go",
      "ability1_index": 1,
      "ability2_index": 0,
      "winner": "python",
      "loser": "go",
      "winner_hp_remaining": 40,
      "turns_taken": 7,
      "winner_ability_used": "Ecosystem Call",
      "loser_ability_used": "Fast Compilation",
      "damage_dealt": {
        "python": 105,
        "go": 60
      }
    },
    {
      "battle_num": 57,
      "language1": "python",
      "language2": "go",
      "ability1_index": 1,
      "ability2_index": 0,
      "winner": "python",
      "loser": "go",
      "winner_hp_remaining": 40,
      "turns_taken": 7,
      "winner_ability_used": "Ecosystem Call",
      "loser_ability_used": "Fast Compilation",
      "damage_dealt": {
        "python": 105,
        "go": 60
      }
    },
    {
      "battle_num": 58,
      "language1": "python",
      "language2": "go",
      "ability1_index": 1,
      "ability2_index": 1,
      "winner": "go",
      "loser": "python",
      "winner_hp_remaining": 25,
      "turns_taken": 5,
      "winner_ability_used": "Goroutine Swarm",
      "loser_ability_used": "Ecosystem Call",
      "damage_dealt": {
        "python": 75,
        "go": 121.34330235492217
      }
    },
    {
      "battle_num": 59,
      "language1": "python",
      "language2": "go",
      "ability1_index": 0,
      "ability2_index": 0,
      "winner": "python",
      "loser": "go",
      "winner_hp_remaining": 10,
      "turns_taken": 10,
      "winner_ability_used": "Rapid Prototype",
      "loser_ability_used": "Fast Compilation",
      "damage_dealt": {
        "python": 100,
        "go": 90
      }
    },
    {
      "battle_num": 60,
      "language1": "python",
      "language2": "go",
      "ability1_index": 1,
      "ability2_index": 1,
      "winner": "go",
      "loser": "python",
      "winner_hp_remaining": 40,
      "turns_taken": 4,
      "winner_ability_used": "Goroutine Swarm",
      "loser_ability_used": "Ecosystem Call",
      "damage_dealt": {
        "python": 60,
        "go": 121.583159323511
      }
    },
    {
      "battle_num": 61,
      "language1": "python",
      "language2": "go",
      "ability1_index": 0,
      "ability2_index": 1,
      "winner": "go",
      "loser": "python",
      "winner_hp_remaining": 70,
      "turns_taken": 3,
      "winner_ability_used": "Goroutine Swarm",
      "loser_ability_used": "Rapid Prototype",
      "damage_dealt": {
        "python": 30,
        "go": 123.57541654546726
      }
    },
    {
      "battle_num": 62,
      "language1": "python",
      "language2": "go",
      "ability1_index": 0,
      "ability2_index": 1,
      "winner": "go",
      "loser": "python",
      "winner_hp_remaining": 70,
      "turns_taken": 3,
      "winner_ability_used": "Goroutine Swarm",
      "loser_ability_used": "Rapid Prototype",
      "damage_dealt": {
        "python": 30,
        "go": 125.66387573693407
      }
    },
    {
      "battle_num": 63,
      "language1": "python",
      "language2": "go",
      "ability1_index": 1,
      "ability2_index": 0,
      "winner": "python",
      "loser": "go",
      "winner_hp_remaining": 40,
      "turns_taken": 7,
      "winner_ability_used": "Ecosystem Call",
      "loser_ability_used": "Fast Compilation",
      "damage_dealt": {
        "python": 105,
        "go": 60
      }
    },
    {
      "battle_num": 64,
      "language1": "python",
      "language2": "go",
      "ability1_index": 1,
      "ability2_index": 1,
      "winner": "go",
      "loser": "python",
      "winner_hp_remaining": 55,
      "turns_taken": 3,
      "winner_ability_used": "Goroutine Swarm",
      "loser_ability_used": "Ecosystem Call",
      "damage_dealt": {
        "python": 45,
        "go": 127.4371028396946
      }
    },
    {
      "battle_num": 65,
      "language1": "python",
      "language2": "go",
      "ability1_index": 1,
      "ability2_index": 0,
      "winner": "python",
      "loser": "go",
      "winner_hp_remaining": 40,
      "turns_taken": 7,
      "winner_ability_used": "Ecosystem Call",
      "loser_ability_used": "Fast Compilation",
      "damage_dealt": {
        "python": 105,
        "go": 60
      }
    },
    {
      "battle_num": 66,
      "language1": "python",
      "language2": "go",
      "ability1_index": 1,
      "ability2_index": 1,
      "winner": "go",
      "loser": "python",
      "winner_hp_remaining": 40,
      "turns_taken": 4,
      "winner_ability_used": "Goroutine Swarm",
      "loser_ability_used": "Ecosystem Call",
      "damage_dealt": {
        "python": 60,
        "go": 124.19715420664875
      }
    },
    {
      "battle_num": 67,
      "language1": "python",
      "language2": "go",
      "ability1_index": 0,
      "ability2_index": 0,
      "winner": "python",
      "loser": "go",
      "winner_hp_remaining": 10,
      "turns_taken": 10,
      "winner_ability_used": "Rapid Prototype",
      "loser_ability_used": "Fast Compilation",
      "damage_dealt": {
        "python": 100,
        "go": 90
      }
    },
    {
      "battle_num": 68,
      "language1": "python",
      "language2": "go",
      "ability1_index": 1,
      "ability2_index": 0,
      "winner": "python",
      "loser": "go",
      "winner_hp_remaining": 40,
      "turns_taken": 7,
      "winner_ability_used": "Ecosystem Call",
      "loser_ability_used": "Fast Compilation",
      "damage_dealt": {
        "python": 105,
        "go": 60
      }
    },
    {
      "battle_num": 69,
      "language1": "python",
      "language2": "go",
      "ability1_index": 0,
      "ability2_index": 1,
      "winner": "go",
      "loser": "python",
      "winner_hp_remaining": 60,
      "turns_taken": 4,
      "winner_ability_used": "Goroutine Swarm",
      "loser_ability_used": "Rapid Prototype",
      "damage_dealt": {
        "python": 40,
        "go": 122.51013357216165
      }
    },
    {
      "battle_num": 70,
      "language1": "python",
      "language2": "go",
      "ability1_index": 1,
      "ability2_index": 1,
      "winner": "go",
      "loser": "python",
      "winner_hp_remaining": 25,
      "turns_taken": 5,
      "winner_ability_used": "Goroutine Swarm",
      "loser_ability_used": "Ecosystem Call",
      "damage_dealt": {
        "python": 75,
        "go": 132.38390129195227
      }
    },
    {
      "battle_num": 71,
      "language1": "python",
      "language2": "go",
      "ability1_index": 1,
      "ability2_index": 1,
      "winner": "go",
      "loser": "python",
      "winner_hp_remaining": 40,
      "turns_taken": 4,
      "winner_ability_used": "Goroutine Swarm",
      "loser_ability_used": "Ecosystem Call",
      "damage_dealt": {
        "python": 60,
        "go": 123.8791142437215
      }
    },
    {
      "battle_num": 72,
      "language1": "python",
      "language2": "go",
      "ability1_index": 1,
      "ability2_index": 0,
      "winner": "python",
      "loser": "go",
      "winner_hp_remaining": 40,
      "turns_taken": 7,
      "winner_ability_used": "Ecosystem Call",
      "loser_ability_used": "Fast Compilation",
      "damage_dealt": {
        "python": 105,
        "go": 60
      }
    },
    {
      "battle_num": 73,
      "language1": "python",
      "language2": "go",
      "ability1_index": 0,
      "ability2_index": 0,
      "winner": "python",
      "loser": "go",
      "winner_hp_remaining": 10,
      "turns_taken": 10,
      "winner_ability_used": "Rapid Prototype",
      "loser_ability_used": "Fast Compilation",
      "damage_dealt": {
        "python": 100,
        "go": 90
      }
    },
    {
      "battle_num": 74,
      "language1": "python",
      "language2": "go",
      "ability1_index": 0,
      "ability2_index": 0,
      "winner": "python",
      "loser": "go",
      "winner_hp_remaining": 10,
      "turns_taken": 10,
      "winner_ability_used": "Rapid Prototype",
      "loser_ability_used": "Fast Compilation",
      "damage_dealt": {
        "python": 100,
        "go": 90
      }
    },
    {
      "battle_num": 75,
      "language1": "python",
      "language2": "go",
      "ability1_index": 1,
      "ability2_index": 1,
      "winner": "go",
      "loser": "python",
      "winner_hp_remaining": 55,
      "turns_taken": 3,
      "winner_ability_used": "Goroutine Swarm",
      "loser_ability_used": "Ecosystem Call",
      "damage_dealt": {
        "python": 45,
        "go": 126.49493586962987
      }
    },
    {
      "battle_num": 76,
      "language1": "python",
      "language2": "go",
      "ability1_index": 1,
      "ability2_index": 1,
      "winner": "go",
      "loser": "python",
      "winner_hp_remaining": 40,
      "turns_taken": 4,
      "winner_ability_used": "Goroutine Swarm",
      "loser_ability_used": "Ecosystem Call",
      "damage_dealt": {
        "python": 60,
        "go": 122.0200399026188
      }
    },
    {
      "battle_num": 77,
      "language1": "python",
      "language2": "go",
      "ability1_index": 0,
      "ability2_index": 1,
      "winner": "go",
      "loser": "python",
      "winner_hp_remaining": 70,
      "turns_taken": 3,
      "winner_ability_used": "Goroutine Swarm",
      "loser_ability_used": "Rapid Prototype",
      "damage_dealt": {
        "python": 30,
        "go": 126.1074450857617
      }
    },
    {
      "battle_num": 78,
      "language1": "python",
      "language2": "go",
      "ability1_index": 1,
      "ability2_index": 1,
      "winner": "go",
      "loser": "python",
      "winner_hp_remaining": 40,
      "turns_taken": 4,
      "winner_ability_used": "Goroutine Swarm",
      "loser_ability_used": "Ecosystem Call",
      "damage_dealt": {
        "python": 60,
        "go": 121.7414437819135
      }
    },
    {
      "battle_num": 79,
      "language1": "python",
      "language2": "go",
      "ability1_index": 0,
      "ability2_index": 0,
      "winner": "python",
      "loser": "go",
      "winner_hp_remaining": 10,
      "turns_taken": 10,
      "winner_ability_used": "Rapid Prototype",
      "loser_ability_used": "Fast Compilation",
      "damage_dealt": {
        "python": 100,
        "go": 90
      }
    },
    {
      "battle_num": 80,
      "language1": "python",
      "language2": "go",
      "ability1_index": 1,
      "ability2_index": 1,
      "winner": "go",
      "loser": "python",
      "winner_hp_remaining": 55,
      "turns_taken": 3,
      "winner_ability_used": "Goroutine Swarm",
      "loser_ability_used": "Ecosystem Call",
      "damage_dealt": {
        "python": 45,
        "go": 123.07262827008796
      }
    },
    {
      "battle_num": 81,
      "language1": "python",
      "language2": "go",
      "ability1_index": 1,
      "ability2_index": 1,
      "winner": "go",
      "loser": "python",
      "winner_hp_remaining": 55,
      "turns_taken": 3,
      "winner_ability_used": "Goroutine Swarm",
      "loser_ability_used": "Ecosystem Call",
      "damage_dealt": {
        "python": 45,
        "go": 127.54647015733947
      }
    },
    {
      "battle_num": 82,
      "language1": "python",
      "language2": "go",
      "ability1_index": 0,
      "ability2_index": 0,
      "winner": "python",
      "loser": "go",
      "winner_hp_remaining": 10,
      "turns_taken": 10,
      "winner_ability_used": "Rapid Prototype",
      "loser_ability_used": "Fast Compilation",
      "damage_dealt": {
        "python": 100,
        "go": 90
      }
    },
    {
      "battle_num": 83,
      "language1": "python",
      "language2": "go",
      "ability1_index": 1,
      "ability2_index": 0,
      "winner": "python",
      "loser": "go",
      "winner_hp_remaining": 40,
      "turns_taken": 7,
      "winner_ability_used": "Ecosystem Call",
      "loser_ability_used": "Fast Compilation",
      "damage_dealt": {
        "python": 105,
        "go": 60
      }
    },
    {
      "battle_num": 84,
      "language1": "python",
      "language2": "go",
      "ability1_index": 1,
      "ability2_index": 0,
      "winner": "python",
      "loser": "go",
      "winner_hp_remaining": 40,
      "turns_taken": 7,
      "winner_ability_used": "Ecosystem Call",
      "loser_ability_used": "Fast Compilation",
      "damage_dealt": {
        "python": 105,
        "go": 60
      }
    },
    {
      "battle_num": 85,
      "language1": "python",
      "language2": "go",
      "ability1_index": 1,
      "ability2_index": 1,
      "winner": "go",
      "loser": "python",
      "winner_hp_remaining": 55,
      "turns_taken": 3,
      "winner_ability_used": "Goroutine Swarm",
      "loser_ability_used": "Ecosystem Call",
      "damage_dealt": {
        "python": 45,
        "go": 121.67975347367297
      }
    },
    {
      "battle_num": 86,
      "language1": "python",
      "language2": "go",
      "ability1_index": 1,
      "ability2_index": 1,
      "winner": "go",
      "loser": "python",
      "winner_hp_remaining": 55,
      "turns_taken": 3,
      "winner_ability_used": "Goroutine Swarm",
      "loser_ability_used": "Ecosystem Call",
      "damage_dealt": {
        "python": 45,
        "go": 130.30083804497008
      }
    },
    {
      "battle_num": 87,
      "language1": "python",
      "language2": "go",
      "ability1_index": 0,
      "ability2_index": 1,
      "winner": "go",
      "loser": "python",
      "winner_hp_remaining": 70,
      "turns_taken": 3,
      "winner_ability_used": "Goroutine Swarm",
      "loser_ability_used": "Rapid Prototype",
      "damage_dealt": {
        "python": 30,
        "go": 121.81686759461252
      }
    },
    {
      "battle_num": 88,
      "language1": "python",
      "language2": "go",
      "ability1_index": 1,
      "ability2_index": 1,
      "winner": "go",
      "loser": "python",
      "winner_hp_remaining": 55,
      "turns_taken": 3,
      "winner_ability_used": "Goroutine Swarm",
      "loser_ability_used": "Ecosystem Call",
      "damage_dealt": {
        "python": 45,
        "go": 124.29678432982931
      }
    },
    {
      "battle_num": 89,
      "language1": "python",
      "language2": "go",
      "ability1_index": 1,
      "ability2_index": 0,
      "winner": "python",
      "loser": "go",
      "winner_hp_remaining": 40,
      "turns_taken": 7,
      "winner_ability_used": "Ecosystem Call",
      "loser_ability_used": "Fast Compilation",
      "damage_dealt": {
        "python": 105,
        "go": 60
      }
    },
    {
      "battle_num": 90,
      "language1": "python",
      "language2": "go",
      "ability1_index": 0,
      "ability2_index": 1,
      "winner": "go",
      "loser": "python",
      "winner_hp_remaining": 70,
      "turns_taken": 3,
      "winner_ability_used": "Goroutine Swarm",
      "loser_ability_used": "Rapid Prototype",
      "damage_dealt": {
        "python": 30,
        "go": 127.1780638842933
      }
    },
    {
      "battle_num": 91,
      "language1": "python",
      "language2": "go",
      "ability1_index": 0,
      "ability2_index": 0,
      "winner": "python",
      "loser": "go",
      "winner_hp_remaining": 10,
      "turns_taken": 10,
      "winner_ability_used": "Rapid Prototype",
      "loser_ability_used": "Fast Compilation",
      "damage_dealt": {
        "python": 100,
        "go": 90
      }
    },
    {
      "battle_num": 92,
      "language1": "python",
      "language2": "go",
      "ability1_index": 0,
      "ability2_index": 1,
      "winner": "go",
      "loser": "python",
      "winner_hp_remaining": 60,
      "turns_taken": 4,
      "winner_ability_used": "Goroutine Swarm",
      "loser_ability_used": "Rapid Prototype",
      "damage_dealt": {
        "python": 40,
        "go": 127.23677836193744
      }
    },
    {
      "battle_num": 93,
      "language1": "python",
      "language2": "go",
      "ability1_index": 0,
      "ability2_index": 0,
      "winner": "python",
      "loser": "go",
      "winner_hp_remaining": 10,
      "turns_taken": 10,
      "winner_ability_used": "Rapid Prototype",
      "loser_ability_used": "Fast Compilation",
      "damage_dealt": {
        "python": 100,
        "go": 90
      }
    },
    {
      "battle_num": 94,
      "language1": "python",
      "language2": "go",
      "ability1_index": 0,
      "ability2_index": 1,
      "winner": "go",
      "loser": "python",
      "winner_hp_remaining": 50,
      "turns_taken": 5,
      "winner_ability_used": "Goroutine Swarm",
      "loser_ability_used": "Rapid Prototype",
      "damage_dealt": {
        "python": 50,
        "go": 127.4269382642872
      }
    },
    {
      "battle_num": 95,
      "language1": "python",
      "language2": "go",
      "ability1_index": 0,
      "ability2_index": 0,
      "winner": "python",
      "loser": "go",
      "winner_hp_remaining": 10,
      "turns_taken": 10,
      "winner_ability_used": "Rapid Prototype",
      "loser_ability_used": "Fast Compilation",
      "damage_dealt": {
        "python": 100,
        "go": 90
      }
    },
    {
      "battle_num": 96,
      "language1": "python",
      "language2": "go",
      "ability1_index": 1,
      "ability2_index": 1,
      "winner": "go",
      "loser": "python",
      "winner_hp_remaining": 55,
      "turns_taken": 3,
      "winner_ability_used": "Goroutine Swarm",
      "loser_ability_used": "Ecosystem Call",
      "damage_dealt": {
        "python": 45,
        "go": 131.03563988237613
      }
    },
    {
      "battle_num": 97,
      "language1": "python",
      "language2": "go",
      "ability1_index": 0,
      "ability2_index": 0,
      "winner": "python",
      "loser": "go",
      "winner_hp_remaining": 10,
      "turns_taken": 10,
      "winner_ability_used": "Rapid Prototype",
      "loser_ability_used": "Fast Compilation",
      "damage_dealt": {
        "python": 100,
        "go": 90
      }
    },
    {
      "battle_num": 98,
      "language1": "python",
      "language2": "go",
      "ability1_index": 0,
      "ability2_index": 0,
      "winner": "python",
      "loser": "go",
      "winner_hp_remaining": 10,
      "turns_taken": 10,
      "winner_ability_used": "Rapid Prototype",
      "loser_ability_used": "Fast Compilation",
      "damage_dealt": {
        "python": 100,
        "go": 90
      }
    },
    {
      "battle_num": 99,
      "language1": "python",
      "language2": "go",
      "ability1_index": 0,
      "ability2_index": 0,
      "winner": "python",
      "loser": "go",
      "winner_hp_remaining": 10,
      "turns_taken": 10,
      "winner_ability_used": "Rapid Prototype",
      "loser_ability_used": "Fast Compilation",
      "damage_dealt": {
        "python": 100,
        "go": 90
      }
    }
  ]
}